{
  "countries": [
    {
      "id": "AT",
      "full_name_english": "Austria",
      "available_regions": [
        {
          "id": 102,
          "code": "BL",
          "name": "Burgenland"
        },
        {
          "id": 99,
          "code": "KN",
          "name": "Kärnten"
        },
        {
          "id": 96,
          "code": "NO",
          "name": "Niederösterreich"
        },
        {
          "id": 97,
          "code": "OO",
          "name": "Oberösterreich"
        },
        {
          "id": 98,
          "code": "SB",
          "name": "Salzburg"
        },
        {
          "id": 100,
          "code": "ST",
          "name": "Steiermark"
        },
        {
          "id": 101,
          "code": "TI",
          "name": "Tirol"
        },
        {
          "id": 103,
          "code": "VB",
          "name": "Vorarlberg"
        },
        {
          "id": 95,
          "code": "WI",
          "name": "Wien"
        }
      ]
    },
    {
      "id": "BE",
      "full_name_english": "Belgium",
      "available_regions": [
        {
          "id": 620,
          "code": "VAN",
          "name": "Antwerpen"
        },
        {
          "id": 621,
          "code": "WBR",
          "name": "Brabant wallon"
        },
        {
          "id": 622,
          "code": "BRU",
          "name": "Brussels-Capital Region"
        },
        {
          "id": 623,
          "code": "WHT",
          "name": "Hainaut"
        },
        {
          "id": 625,
          "code": "WLG",
          "name": "Liège"
        },
        {
          "id": 624,
          "code": "VLI",
          "name": "Limburg"
        },
        {
          "id": 626,
          "code": "WLX",
          "name": "Luxembourg"
        },
        {
          "id": 627,
          "code": "WNA",
          "name": "Namur"
        },
        {
          "id": 628,
          "code": "VOV",
          "name": "Oost-Vlaanderen"
        },
        {
          "id": 629,
          "code": "VBR",
          "name": "Vlaams-Brabant"
        },
        {
          "id": 630,
          "code": "VWV",
          "name": "West-Vlaanderen"
        }
      ]
    },
    {
      "id": "BG",
      "full_name_english": "Bulgaria",
      "available_regions": [
        {
          "id": 640,
          "code": "BG-01",
          "name": "Blagoevgrad"
        },
        {
          "id": 641,
          "code": "BG-02",
          "name": "Burgas"
        },
        {
          "id": 647,
          "code": "BG-08",
          "name": "Dobrich"
        },
        {
          "id": 646,
          "code": "BG-07",
          "name": "Gabrovo"
        },
        {
          "id": 665,
          "code": "BG-26",
          "name": "Haskovo"
        },
        {
          "id": 648,
          "code": "BG-09",
          "name": "Kardzhali"
        },
        {
          "id": 649,
          "code": "BG-10",
          "name": "Kyustendil"
        },
        {
          "id": 650,
          "code": "BG-11",
          "name": "Lovech"
        },
        {
          "id": 651,
          "code": "BG-12",
          "name": "Montana"
        },
        {
          "id": 652,
          "code": "BG-13",
          "name": "Pazardzhik"
        },
        {
          "id": 653,
          "code": "BG-14",
          "name": "Pernik"
        },
        {
          "id": 654,
          "code": "BG-15",
          "name": "Pleven"
        },
        {
          "id": 655,
          "code": "BG-16",
          "name": "Plovdiv"
        },
        {
          "id": 656,
          "code": "BG-17",
          "name": "Razgrad"
        },
        {
          "id": 657,
          "code": "BG-18",
          "name": "Ruse"
        },
        {
          "id": 666,
          "code": "BG-27",
          "name": "Shumen"
        },
        {
          "id": 658,
          "code": "BG-19",
          "name": "Silistra"
        },
        {
          "id": 659,
          "code": "BG-20",
          "name": "Sliven"
        },
        {
          "id": 660,
          "code": "BG-21",
          "name": "Smolyan"
        },
        {
          "id": 661,
          "code": "BG-22",
          "name": "Sofia City"
        },
        {
          "id": 662,
          "code": "BG-23",
          "name": "Sofia Province"
        },
        {
          "id": 663,
          "code": "BG-24",
          "name": "Stara Zagora"
        },
        {
          "id": 664,
          "code": "BG-25",
          "name": "Targovishte"
        },
        {
          "id": 642,
          "code": "BG-03",
          "name": "Varna"
        },
        {
          "id": 643,
          "code": "BG-04",
          "name": "Veliko Tarnovo"
        },
        {
          "id": 644,
          "code": "BG-05",
          "name": "Vidin"
        },
        {
          "id": 645,
          "code": "BG-06",
          "name": "Vratsa"
        },
        {
          "id": 667,
          "code": "BG-28",
          "name": "Yambol"
        }
      ]
    },
    {
      "id": "CZ",
      "full_name_english": "Czechia",
      "available_regions": [
        {
          "id": 759,
          "code": "CZ-31",
          "name": "Jihočeský kraj"
        },
        {
          "id": 767,
          "code": "CZ-64",
          "name": "Jihomoravský kraj"
        },
        {
          "id": 761,
          "code": "CZ-41",
          "name": "Karlovarský kraj"
        },
        {
          "id": 766,
          "code": "CZ-63",
          "name": "Kraj Vysočina"
        },
        {
          "id": 764,
          "code": "CZ-52",
          "name": "Královéhradecký kraj"
        },
        {
          "id": 763,
          "code": "CZ-51",
          "name": "Liberecký kraj"
        },
        {
          "id": 770,
          "code": "CZ-80",
          "name": "Moravskoslezský kraj"
        },
        {
          "id": 768,
          "code": "CZ-71",
          "name": "Olomoucký kraj"
        },
        {
          "id": 765,
          "code": "CZ-53",
          "name": "Pardubický kraj"
        },
        {
          "id": 760,
          "code": "CZ-32",
          "name": "Plzeňský kraj"
        },
        {
          "id": 757,
          "code": "CZ-10",
          "name": "Praha, Hlavní město"
        },
        {
          "id": 758,
          "code": "CZ-20",
          "name": "Středočeský kraj"
        },
        {
          "id": 762,
          "code": "CZ-42",
          "name": "Ústecký kraj"
        },
        {
          "id": 769,
          "code": "CZ-72",
          "name": "Zlínský kraj"
        }
      ]
    },
    {
      "id": "DE",
      "full_name_english": "Germany",
      "available_regions": [
        {
          "id": 80,
          "code": "BAW",
          "name": "Baden-Württemberg"
        },
        {
          "id": 81,
          "code": "BAY",
          "name": "Bayern"
        },
        {
          "id": 82,
          "code": "BER",
          "name": "Berlin"
        },
        {
          "id": 83,
          "code": "BRG",
          "name": "Brandenburg"
        },
        {
          "id": 84,
          "code": "BRE",
          "name": "Bremen"
        },
        {
          "id": 85,
          "code": "HAM",
          "name": "Hamburg"
        },
        {
          "id": 86,
          "code": "HES",
          "name": "Hessen"
        },
        {
          "id": 87,
          "code": "MEC",
          "name": "Mecklenburg-Vorpommern"
        },
        {
          "id": 79,
          "code": "NDS",
          "name": "Niedersachsen"
        },
        {
          "id": 88,
          "code": "NRW",
          "name": "Nordrhein-Westfalen"
        },
        {
          "id": 89,
          "code": "RHE",
          "name": "Rheinland-Pfalz"
        },
        {
          "id": 90,
          "code": "SAR",
          "name": "Saarland"
        },
        {
          "id": 91,
          "code": "SAS",
          "name": "Sachsen"
        },
        {
          "id": 92,
          "code": "SAC",
          "name": "Sachsen-Anhalt"
        },
        {
          "id": 93,
          "code": "SCN",
          "name": "Schleswig-Holstein"
        },
        {
          "id": 94,
          "code": "THE",
          "name": "Thüringen"
        }
      ]
    },
    {
      "id": "DK",
      "full_name_english": "Denmark",
      "available_regions": [
        {
          "id": 771,
          "code": "DK-84",
          "name": "Hovedstaden"
        },
        {
          "id": 772,
          "code": "DK-82",
          "name": "Midtjylland"
        },
        {
          "id": 773,
          "code": "DK-81",
          "name": "Nordjylland"
        },
        {
          "id": 774,
          "code": "DK-85",
          "name": "Sjælland"
        },
        {
          "id": 775,
          "code": "DK-83",
          "name": "Syddanmark"
        }
      ]
    },
    {
      "id": "EE",
      "full_name_english": "Estonia",
      "available_regions": [
        {
          "id": 340,
          "code": "EE-37",
          "name": "Harjumaa"
        },
        {
          "id": 341,
          "code": "EE-39",
          "name": "Hiiumaa"
        },
        {
          "id": 342,
          "code": "EE-44",
          "name": "Ida-Virumaa"
        },
        {
          "id": 344,
          "code": "EE-51",
          "name": "Järvamaa"
        },
        {
          "id": 343,
          "code": "EE-49",
          "name": "Jõgevamaa"
        },
        {
          "id": 346,
          "code": "EE-59",
          "name": "Lääne-Virumaa"
        },
        {
          "id": 345,
          "code": "EE-57",
          "name": "Läänemaa"
        },
        {
          "id": 348,
          "code": "EE-67",
          "name": "Pärnumaa"
        },
        {
          "id": 347,
          "code": "EE-65",
          "name": "Põlvamaa"
        },
        {
          "id": 349,
          "code": "EE-70",
          "name": "Raplamaa"
        },
        {
          "id": 350,
          "code": "EE-74",
          "name": "Saaremaa"
        },
        {
          "id": 351,
          "code": "EE-78",
          "name": "Tartumaa"
        },
        {
          "id": 352,
          "code": "EE-82",
          "name": "Valgamaa"
        },
        {
          "id": 353,
          "code": "EE-84",
          "name": "Viljandimaa"
        },
        {
          "id": 354,
          "code": "EE-86",
          "name": "Võrumaa"
        }
      ]
    },
    {
      "id": "FI",
      "full_name_english": "Finland",
      "available_regions": [
        {
          "id": 339,
          "code": "Ahvenanmaa",
          "name": "Ahvenanmaa"
        },
        {
          "id": 333,
          "code": "Etelä-Karjala",
          "name": "Etelä-Karjala"
        },
        {
          "id": 326,
          "code": "Etelä-Pohjanmaa",
          "name": "Etelä-Pohjanmaa"
        },
        {
          "id": 325,
          "code": "Etelä-Savo",
          "name": "Etelä-Savo"
        },
        {
          "id": 337,
          "code": "Itä-Uusimaa",
          "name": "Itä-Uusimaa"
        },
        {
          "id": 322,
          "code": "Kainuu",
          "name": "Kainuu"
        },
        {
          "id": 335,
          "code": "Kanta-Häme",
          "name": "Kanta-Häme"
        },
        {
          "id": 330,
          "code": "Keski-Pohjanmaa",
          "name": "Keski-Pohjanmaa"
        },
        {
          "id": 331,
          "code": "Keski-Suomi",
          "name": "Keski-Suomi"
        },
        {
          "id": 338,
          "code": "Kymenlaakso",
          "name": "Kymenlaakso"
        },
        {
          "id": 320,
          "code": "Lappi",
          "name": "Lappi"
        },
        {
          "id": 334,
          "code": "Päijät-Häme",
          "name": "Päijät-Häme"
        },
        {
          "id": 328,
          "code": "Pirkanmaa",
          "name": "Pirkanmaa"
        },
        {
          "id": 327,
          "code": "Pohjanmaa",
          "name": "Pohjanmaa"
        },
        {
          "id": 323,
          "code": "Pohjois-Karjala",
          "name": "Pohjois-Karjala"
        },
        {
          "id": 321,
          "code": "Pohjois-Pohjanmaa",
          "name": "Pohjois-Pohjanmaa"
        },
        {
          "id": 324,
          "code": "Pohjois-Savo",
          "name": "Pohjois-Savo"
        },
        {
          "id": 329,
          "code": "Satakunta",
          "name": "Satakunta"
        },
        {
          "id": 336,
          "code": "Uusimaa",
          "name": "Uusimaa"
        },
        {
          "id": 332,
          "code": "Varsinais-Suomi",
          "name": "Varsinais-Suomi"
        }
      ]
    },
    {
      "id": "FR",
      "full_name_english": "France",
      "available_regions": [
        {
          "id": 182,
          "code": "1",
          "name": "Ain"
        },
        {
          "id": 183,
          "code": "2",
          "name": "Aisne"
        },
        {
          "id": 184,
          "code": "3",
          "name": "Allier"
        },
        {
          "id": 185,
          "code": "4",
          "name": "Alpes-de-Haute-Provence"
        },
        {
          "id": 187,
          "code": "6",
          "name": "Alpes-Maritimes"
        },
        {
          "id": 188,
          "code": "7",
          "name": "Ardèche"
        },
        {
          "id": 189,
          "code": "8",
          "name": "Ardennes"
        },
        {
          "id": 190,
          "code": "9",
          "name": "Ariège"
        },
        {
          "id": 191,
          "code": "10",
          "name": "Aube"
        },
        {
          "id": 192,
          "code": "11",
          "name": "Aude"
        },
        {
          "id": 193,
          "code": "12",
          "name": "Aveyron"
        },
        {
          "id": 249,
          "code": "67",
          "name": "Bas-Rhin"
        },
        {
          "id": 194,
          "code": "13",
          "name": "Bouches-du-Rhône"
        },
        {
          "id": 195,
          "code": "14",
          "name": "Calvados"
        },
        {
          "id": 196,
          "code": "15",
          "name": "Cantal"
        },
        {
          "id": 197,
          "code": "16",
          "name": "Charente"
        },
        {
          "id": 198,
          "code": "17",
          "name": "Charente-Maritime"
        },
        {
          "id": 199,
          "code": "18",
          "name": "Cher"
        },
        {
          "id": 200,
          "code": "19",
          "name": "Corrèze"
        },
        {
          "id": 201,
          "code": "2A",
          "name": "Corse-du-Sud"
        },
        {
          "id": 203,
          "code": "21",
          "name": "Côte-d'Or"
        },
        {
          "id": 204,
          "code": "22",
          "name": "Côtes-d'Armor"
        },
        {
          "id": 205,
          "code": "23",
          "name": "Creuse"
        },
        {
          "id": 261,
          "code": "79",
          "name": "Deux-Sèvres"
        },
        {
          "id": 206,
          "code": "24",
          "name": "Dordogne"
        },
        {
          "id": 207,
          "code": "25",
          "name": "Doubs"
        },
        {
          "id": 208,
          "code": "26",
          "name": "Drôme"
        },
        {
          "id": 273,
          "code": "91",
          "name": "Essonne"
        },
        {
          "id": 209,
          "code": "27",
          "name": "Eure"
        },
        {
          "id": 210,
          "code": "28",
          "name": "Eure-et-Loir"
        },
        {
          "id": 211,
          "code": "29",
          "name": "Finistère"
        },
        {
          "id": 212,
          "code": "30",
          "name": "Gard"
        },
        {
          "id": 214,
          "code": "32",
          "name": "Gers"
        },
        {
          "id": 215,
          "code": "33",
          "name": "Gironde"
        },
        {
          "id": 250,
          "code": "68",
          "name": "Haut-Rhin"
        },
        {
          "id": 202,
          "code": "2B",
          "name": "Haute-Corse"
        },
        {
          "id": 213,
          "code": "31",
          "name": "Haute-Garonne"
        },
        {
          "id": 225,
          "code": "43",
          "name": "Haute-Loire"
        },
        {
          "id": 234,
          "code": "52",
          "name": "Haute-Marne"
        },
        {
          "id": 252,
          "code": "70",
          "name": "Haute-Saône"
        },
        {
          "id": 256,
          "code": "74",
          "name": "Haute-Savoie"
        },
        {
          "id": 269,
          "code": "87",
          "name": "Haute-Vienne"
        },
        {
          "id": 186,
          "code": "5",
          "name": "Hautes-Alpes"
        },
        {
          "id": 247,
          "code": "65",
          "name": "Hautes-Pyrénées"
        },
        {
          "id": 274,
          "code": "92",
          "name": "Hauts-de-Seine"
        },
        {
          "id": 216,
          "code": "34",
          "name": "Hérault"
        },
        {
          "id": 217,
          "code": "35",
          "name": "Ille-et-Vilaine"
        },
        {
          "id": 218,
          "code": "36",
          "name": "Indre"
        },
        {
          "id": 219,
          "code": "37",
          "name": "Indre-et-Loire"
        },
        {
          "id": 220,
          "code": "38",
          "name": "Isère"
        },
        {
          "id": 221,
          "code": "39",
          "name": "Jura"
        },
        {
          "id": 222,
          "code": "40",
          "name": "Landes"
        },
        {
          "id": 223,
          "code": "41",
          "name": "Loir-et-Cher"
        },
        {
          "id": 224,
          "code": "42",
          "name": "Loire"
        },
        {
          "id": 226,
          "code": "44",
          "name": "Loire-Atlantique"
        },
        {
          "id": 227,
          "code": "45",
          "name": "Loiret"
        },
        {
          "id": 228,
          "code": "46",
          "name": "Lot"
        },
        {
          "id": 229,
          "code": "47",
          "name": "Lot-et-Garonne"
        },
        {
          "id": 230,
          "code": "48",
          "name": "Lozère"
        },
        {
          "id": 231,
          "code": "49",
          "name": "Maine-et-Loire"
        },
        {
          "id": 232,
          "code": "50",
          "name": "Manche"
        },
        {
          "id": 233,
          "code": "51",
          "name": "Marne"
        },
        {
          "id": 235,
          "code": "53",
          "name": "Mayenne"
        },
        {
          "id": 236,
          "code": "54",
          "name": "Meurthe-et-Moselle"
        },
        {
          "id": 237,
          "code": "55",
          "name": "Meuse"
        },
        {
          "id": 238,
          "code": "56",
          "name": "Morbihan"
        },
        {
          "id": 239,
          "code": "57",
          "name": "Moselle"
        },
        {
          "id": 240,
          "code": "58",
          "name": "Nièvre"
        },
        {
          "id": 241,
          "code": "59",
          "name": "Nord"
        },
        {
          "id": 242,
          "code": "60",
          "name": "Oise"
        },
        {
          "id": 243,
          "code": "61",
          "name": "Orne"
        },
        {
          "id": 257,
          "code": "75",
          "name": "Paris"
        },
        {
          "id": 244,
          "code": "62",
          "name": "Pas-de-Calais"
        },
        {
          "id": 245,
          "code": "63",
          "name": "Puy-de-Dôme"
        },
        {
          "id": 246,
          "code": "64",
          "name": "Pyrénées-Atlantiques"
        },
        {
          "id": 248,
          "code": "66",
          "name": "Pyrénées-Orientales"
        },
        {
          "id": 251,
          "code": "69",
          "name": "Rhône"
        },
        {
          "id": 253,
          "code": "71",
          "name": "Saône-et-Loire"
        },
        {
          "id": 254,
          "code": "72",
          "name": "Sarthe"
        },
        {
          "id": 255,
          "code": "73",
          "name": "Savoie"
        },
        {
          "id": 259,
          "code": "77",
          "name": "Seine-et-Marne"
        },
        {
          "id": 258,
          "code": "76",
          "name": "Seine-Maritime"
        },
        {
          "id": 275,
          "code": "93",
          "name": "Seine-Saint-Denis"
        },
        {
          "id": 262,
          "code": "80",
          "name": "Somme"
        },
        {
          "id": 263,
          "code": "81",
          "name": "Tarn"
        },
        {
          "id": 264,
          "code": "82",
          "name": "Tarn-et-Garonne"
        },
        {
          "id": 272,
          "code": "90",
          "name": "Territoire-de-Belfort"
        },
        {
          "id": 277,
          "code": "95",
          "name": "Val-d'Oise"
        },
        {
          "id": 276,
          "code": "94",
          "name": "Val-de-Marne"
        },
        {
          "id": 265,
          "code": "83",
          "name": "Var"
        },
        {
          "id": 266,
          "code": "84",
          "name": "Vaucluse"
        },
        {
          "id": 267,
          "code": "85",
          "name": "Vendée"
        },
        {
          "id": 268,
          "code": "86",
          "name": "Vienne"
        },
        {
          "id": 270,
          "code": "88",
          "name": "Vosges"
        },
        {
          "id": 271,
          "code": "89",
          "name": "Yonne"
        },
        {
          "id": 260,
          "code": "78",
          "name": "Yvelines"
        }
      ]
    },
    {
      "id": "GR",
      "full_name_english": "Greece",
      "available_regions": [
        {
          "id": 813,
          "code": "GR-69",
          "name": "Ágion Óros"
        },
        {
          "id": 800,
          "code": "GR-A",
          "name": "Anatolikí Makedonía kai Thráki"
        },
        {
          "id": 801,
          "code": "GR-I",
          "name": "Attikí"
        },
        {
          "id": 802,
          "code": "GR-G",
          "name": "Dytikí Elláda"
        },
        {
          "id": 803,
          "code": "GR-C",
          "name": "Dytikí Makedonía"
        },
        {
          "id": 804,
          "code": "GR-F",
          "name": "Ionía Nísia"
        },
        {
          "id": 805,
          "code": "GR-D",
          "name": "Ípeiros"
        },
        {
          "id": 806,
          "code": "GR-B",
          "name": "Kentrikí Makedonía"
        },
        {
          "id": 807,
          "code": "GR-M",
          "name": "Kríti"
        },
        {
          "id": 808,
          "code": "GR-L",
          "name": "Nótio Aigaío"
        },
        {
          "id": 809,
          "code": "GR-J",
          "name": "Pelopónnisos"
        },
        {
          "id": 810,
          "code": "GR-H",
          "name": "Stereá Elláda"
        },
        {
          "id": 811,
          "code": "GR-E",
          "name": "Thessalía"
        },
        {
          "id": 812,
          "code": "GR-K",
          "name": "Vóreio Aigaío"
        }
      ]
    },
    {
      "id": "HR",
      "full_name_english": "Croatia",
      "available_regions": [
        {
          "id": 554,
          "code": "HR-07",
          "name": "Bjelovarsko-bilogorska županija"
        },
        {
          "id": 559,
          "code": "HR-12",
          "name": "Brodsko-posavska županija"
        },
        {
          "id": 566,
          "code": "HR-19",
          "name": "Dubrovačko-neretvanska županija"
        },
        {
          "id": 568,
          "code": "HR-21",
          "name": "Grad Zagreb"
        },
        {
          "id": 565,
          "code": "HR-18",
          "name": "Istarska županija"
        },
        {
          "id": 551,
          "code": "HR-04",
          "name": "Karlovačka županija"
        },
        {
          "id": 553,
          "code": "HR-06",
          "name": "Koprivničko-križevačka županija"
        },
        {
          "id": 549,
          "code": "HR-02",
          "name": "Krapinsko-zagorska županija"
        },
        {
          "id": 556,
          "code": "HR-09",
          "name": "Ličko-senjska županija"
        },
        {
          "id": 567,
          "code": "HR-20",
          "name": "Međimurska županija"
        },
        {
          "id": 561,
          "code": "HR-14",
          "name": "Osječko-baranjska županija"
        },
        {
          "id": 558,
          "code": "HR-11",
          "name": "Požeško-slavonska županija"
        },
        {
          "id": 555,
          "code": "HR-08",
          "name": "Primorsko-goranska županija"
        },
        {
          "id": 562,
          "code": "HR-15",
          "name": "Šibensko-kninska županija"
        },
        {
          "id": 550,
          "code": "HR-03",
          "name": "Sisačko-moslavačka županija"
        },
        {
          "id": 564,
          "code": "HR-17",
          "name": "Splitsko-dalmatinska županija"
        },
        {
          "id": 552,
          "code": "HR-05",
          "name": "Varaždinska županija"
        },
        {
          "id": 557,
          "code": "HR-10",
          "name": "Virovitičko-podravska županija"
        },
        {
          "id": 563,
          "code": "HR-16",
          "name": "Vukovarsko-srijemska županija"
        },
        {
          "id": 560,
          "code": "HR-13",
          "name": "Zadarska županija"
        },
        {
          "id": 548,
          "code": "HR-01",
          "name": "Zagrebačka županija"
        }
      ]
    },
    {
      "id": "HU",
      "full_name_english": "Hungary",
      "available_regions": null
    },
    {
      "id": "IT",
      "full_name_english": "Italy",
      "available_regions": [
        {
          "id": 832,
          "code": "AG",
          "name": "Agrigento"
        },
        {
          "id": 833,
          "code": "AL",
          "name": "Alessandria"
        },
        {
          "id": 834,
          "code": "AN",
          "name": "Ancona"
        },
        {
          "id": 835,
          "code": "AO",
          "name": "Aosta"
        },
        {
          "id": 837,
          "code": "AR",
          "name": "Arezzo"
        },
        {
          "id": 838,
          "code": "AP",
          "name": "Ascoli-Piceno"
        },
        {
          "id": 839,
          "code": "AT",
          "name": "Asti"
        },
        {
          "id": 840,
          "code": "AV",
          "name": "Avellino"
        },
        {
          "id": 841,
          "code": "BA",
          "name": "Bari"
        },
        {
          "id": 842,
          "code": "BT",
          "name": "Barletta-Andria-Trani"
        },
        {
          "id": 843,
          "code": "BL",
          "name": "Belluno"
        },
        {
          "id": 844,
          "code": "BN",
          "name": "Benevento"
        },
        {
          "id": 845,
          "code": "BG",
          "name": "Bergamo"
        },
        {
          "id": 846,
          "code": "BI",
          "name": "Biella"
        },
        {
          "id": 847,
          "code": "BO",
          "name": "Bologna"
        },
        {
          "id": 848,
          "code": "BZ",
          "name": "Bolzano"
        },
        {
          "id": 849,
          "code": "BS",
          "name": "Brescia"
        },
        {
          "id": 850,
          "code": "BR",
          "name": "Brindisi"
        },
        {
          "id": 851,
          "code": "CA",
          "name": "Cagliari"
        },
        {
          "id": 852,
          "code": "CL",
          "name": "Caltanissetta"
        },
        {
          "id": 853,
          "code": "CB",
          "name": "Campobasso"
        },
        {
          "id": 854,
          "code": "CI",
          "name": "Carbonia Iglesias"
        },
        {
          "id": 855,
          "code": "CE",
          "name": "Caserta"
        },
        {
          "id": 856,
          "code": "CT",
          "name": "Catania"
        },
        {
          "id": 857,
          "code": "CZ",
          "name": "Catanzaro"
        },
        {
          "id": 858,
          "code": "CH",
          "name": "Chieti"
        },
        {
          "id": 859,
          "code": "CO",
          "name": "Como"
        },
        {
          "id": 860,
          "code": "CS",
          "name": "Cosenza"
        },
        {
          "id": 861,
          "code": "CR",
          "name": "Cremona"
        },
        {
          "id": 862,
          "code": "KR",
          "name": "Crotone"
        },
        {
          "id": 863,
          "code": "CN",
          "name": "Cuneo"
        },
        {
          "id": 864,
          "code": "EN",
          "name": "Enna"
        },
        {
          "id": 865,
          "code": "FM",
          "name": "Fermo"
        },
        {
          "id": 866,
          "code": "FE",
          "name": "Ferrara"
        },
        {
          "id": 867,
          "code": "FI",
          "name": "Firenze"
        },
        {
          "id": 868,
          "code": "FG",
          "name": "Foggia"
        },
        {
          "id": 869,
          "code": "FC",
          "name": "Forli-Cesena"
        },
        {
          "id": 870,
          "code": "FR",
          "name": "Frosinone"
        },
        {
          "id": 871,
          "code": "GE",
          "name": "Genova"
        },
        {
          "id": 872,
          "code": "GO",
          "name": "Gorizia"
        },
        {
          "id": 873,
          "code": "GR",
          "name": "Grosseto"
        },
        {
          "id": 874,
          "code": "IM",
          "name": "Imperia"
        },
        {
          "id": 875,
          "code": "IS",
          "name": "Isernia"
        },
        {
          "id": 836,
          "code": "AQ",
          "name": "L'Aquila"
        },
        {
          "id": 876,
          "code": "SP",
          "name": "La-Spezia"
        },
        {
          "id": 877,
          "code": "LT",
          "name": "Latina"
        },
        {
          "id": 878,
          "code": "LE",
          "name": "Lecce"
        },
        {
          "id": 879,
          "code": "LC",
          "name": "Lecco"
        },
        {
          "id": 880,
          "code": "LI",
          "name": "Livorno"
        },
        {
          "id": 881,
          "code": "LO",
          "name": "Lodi"
        },
        {
          "id": 882,
          "code": "LU",
          "name": "Lucca"
        },
        {
          "id": 883,
          "code": "MC",
          "name": "Macerata"
        },
        {
          "id": 884,
          "code": "MN",
          "name": "Mantova"
        },
        {
          "id": 885,
          "code": "MS",
          "name": "Massa-Carrara"
        },
        {
          "id": 886,
          "code": "MT",
          "name": "Matera"
        },
        {
          "id": 887,
          "code": "VS",
          "name": "Medio Campidano"
        },
        {
          "id": 888,
          "code": "ME",
          "name": "Messina"
        },
        {
          "id": 889,
          "code": "MI",
          "name": "Milano"
        },
        {
          "id": 890,
          "code": "MO",
          "name": "Modena"
        },
        {
          "id": 891,
          "code": "MB",
          "name": "Monza-Brianza"
        },
        {
          "id": 892,
          "code": "NA",
          "name": "Napoli"
        },
        {
          "id": 893,
          "code": "NO",
          "name": "Novara"
        },
        {
          "id": 894,
          "code": "NU",
          "name": "Nuoro"
        },
        {
          "id": 895,
          "code": "OG",
          "name": "Ogliastra"
        },
        {
          "id": 896,
          "code": "OT",
          "name": "Olbia Tempio"
        },
        {
          "id": 897,
          "code": "OR",
          "name": "Oristano"
        },
        {
          "id": 898,
          "code": "PD",
          "name": "Padova"
        },
        {
          "id": 899,
          "code": "PA",
          "name": "Palermo"
        },
        {
          "id": 900,
          "code": "PR",
          "name": "Parma"
        },
        {
          "id": 901,
          "code": "PV",
          "name": "Pavia"
        },
        {
          "id": 902,
          "code": "PG",
          "name": "Perugia"
        },
        {
          "id": 903,
          "code": "PU",
          "name": "Pesaro-Urbino"
        },
        {
          "id": 904,
          "code": "PE",
          "name": "Pescara"
        },
        {
          "id": 905,
          "code": "PC",
          "name": "Piacenza"
        },
        {
          "id": 906,
          "code": "PI",
          "name": "Pisa"
        },
        {
          "id": 907,
          "code": "PT",
          "name": "Pistoia"
        },
        {
          "id": 908,
          "code": "PN",
          "name": "Pordenone"
        },
        {
          "id": 909,
          "code": "PZ",
          "name": "Potenza"
        },
        {
          "id": 910,
          "code": "PO",
          "name": "Prato"
        },
        {
          "id": 911,
          "code": "RG",
          "name": "Ragusa"
        },
        {
          "id": 912,
          "code": "RA",
          "name": "Ravenna"
        },
        {
          "id": 913,
          "code": "RC",
          "name": "Reggio-Calabria"
        },
        {
          "id": 914,
          "code": "RE",
          "name": "Reggio-Emilia"
        },
        {
          "id": 915,
          "code": "RI",
          "name": "Rieti"
        },
        {
          "id": 916,
          "code": "RN",
          "name": "Rimini"
        },
        {
          "id": 917,
          "code": "RM",
          "name": "Roma"
        },
        {
          "id": 918,
          "code": "RO",
          "name": "Rovigo"
        },
        {
          "id": 919,
          "code": "SA",
          "name": "Salerno"
        },
        {
          "id": 920,
          "code": "SS",
          "name": "Sassari"
        },
        {
          "id": 921,
          "code": "SV",
          "name": "Savona"
        },
        {
          "id": 922,
          "code": "SI",
          "name": "Siena"
        },
        {
          "id": 923,
          "code": "SR",
          "name": "Siracusa"
        },
        {
          "id": 924,
          "code": "SO",
          "name": "Sondrio"
        },
        {
          "id": 925,
          "code": "TA",
          "name": "Taranto"
        },
        {
          "id": 926,
          "code": "TE",
          "name": "Teramo"
        },
        {
          "id": 927,
          "code": "TR",
          "name": "Terni"
        },
        {
          "id": 928,
          "code": "TO",
          "name": "Torino"
        },
        {
          "id": 929,
          "code": "TP",
          "name": "Trapani"
        },
        {
          "id": 930,
          "code": "TN",
          "name": "Trento"
        },
        {
          "id": 931,
          "code": "TV",
          "name": "Treviso"
        },
        {
          "id": 932,
          "code": "TS",
          "name": "Trieste"
        },
        {
          "id": 933,
          "code": "UD",
          "name": "Udine"
        },
        {
          "id": 934,
          "code": "VA",
          "name": "Varese"
        },
        {
          "id": 935,
          "code": "VE",
          "name": "Venezia"
        },
        {
          "id": 936,
          "code": "VB",
          "name": "Verbania"
        },
        {
          "id": 937,
          "code": "VC",
          "name": "Vercelli"
        },
        {
          "id": 938,
          "code": "VR",
          "name": "Verona"
        },
        {
          "id": 939,
          "code": "VV",
          "name": "Vibo-Valentia"
        },
        {
          "id": 940,
          "code": "VI",
          "name": "Vicenza"
        },
        {
          "id": 941,
          "code": "VT",
          "name": "Viterbo"
        }
      ]
    },
    {
      "id": "LT",
      "full_name_english": "Lithuania",
      "available_regions": [
        {
          "id": 475,
          "code": "LT-AL",
          "name": "Alytaus Apskritis"
        },
        {
          "id": 476,
          "code": "LT-KU",
          "name": "Kauno Apskritis"
        },
        {
          "id": 477,
          "code": "LT-KL",
          "name": "Klaipėdos Apskritis"
        },
        {
          "id": 478,
          "code": "LT-MR",
          "name": "Marijampolės Apskritis"
        },
        {
          "id": 479,
          "code": "LT-PN",
          "name": "Panevėžio Apskritis"
        },
        {
          "id": 480,
          "code": "LT-SA",
          "name": "Šiaulių Apskritis"
        },
        {
          "id": 481,
          "code": "LT-TA",
          "name": "Tauragės Apskritis"
        },
        {
          "id": 482,
          "code": "LT-TE",
          "name": "Telšių Apskritis"
        },
        {
          "id": 483,
          "code": "LT-UT",
          "name": "Utenos Apskritis"
        },
        {
          "id": 484,
          "code": "LT-VL",
          "name": "Vilniaus Apskritis"
        }
      ]
    },
    {
      "id": "LU",
      "full_name_english": "Luxembourg",
      "available_regions": null
    },
    {
      "id": "LV",
      "full_name_english": "Latvia",
      "available_regions": [
        {
          "id": 471,
          "code": "Ādažu novads",
          "name": "Ādažu novads"
        },
        {
          "id": 366,
          "code": "Aglonas novads",
          "name": "Aglonas novads"
        },
        {
          "id": 367,
          "code": "LV-AI",
          "name": "Aizkraukles novads"
        },
        {
          "id": 368,
          "code": "Aizputes novads",
          "name": "Aizputes novads"
        },
        {
          "id": 369,
          "code": "Aknīstes novads",
          "name": "Aknīstes novads"
        },
        {
          "id": 370,
          "code": "Alojas novads",
          "name": "Alojas novads"
        },
        {
          "id": 371,
          "code": "Alsungas novads",
          "name": "Alsungas novads"
        },
        {
          "id": 372,
          "code": "LV-AL",
          "name": "Alūksnes novads"
        },
        {
          "id": 373,
          "code": "Amatas novads",
          "name": "Amatas novads"
        },
        {
          "id": 374,
          "code": "Apes novads",
          "name": "Apes novads"
        },
        {
          "id": 375,
          "code": "Auces novads",
          "name": "Auces novads"
        },
        {
          "id": 376,
          "code": "Babītes novads",
          "name": "Babītes novads"
        },
        {
          "id": 377,
          "code": "Baldones novads",
          "name": "Baldones novads"
        },
        {
          "id": 378,
          "code": "Baltinavas novads",
          "name": "Baltinavas novads"
        },
        {
          "id": 379,
          "code": "LV-BL",
          "name": "Balvu novads"
        },
        {
          "id": 380,
          "code": "LV-BU",
          "name": "Bauskas novads"
        },
        {
          "id": 381,
          "code": "Beverīnas novads",
          "name": "Beverīnas novads"
        },
        {
          "id": 382,
          "code": "Brocēnu novads",
          "name": "Brocēnu novads"
        },
        {
          "id": 383,
          "code": "Burtnieku novads",
          "name": "Burtnieku novads"
        },
        {
          "id": 384,
          "code": "Carnikavas novads",
          "name": "Carnikavas novads"
        },
        {
          "id": 387,
          "code": "LV-CE",
          "name": "Cēsu novads"
        },
        {
          "id": 385,
          "code": "Cesvaines novads",
          "name": "Cesvaines novads"
        },
        {
          "id": 386,
          "code": "Ciblas novads",
          "name": "Ciblas novads"
        },
        {
          "id": 388,
          "code": "Dagdas novads",
          "name": "Dagdas novads"
        },
        {
          "id": 355,
          "code": "LV-DGV",
          "name": "Daugavpils"
        },
        {
          "id": 389,
          "code": "LV-DA",
          "name": "Daugavpils novads"
        },
        {
          "id": 390,
          "code": "LV-DO",
          "name": "Dobeles novads"
        },
        {
          "id": 391,
          "code": "Dundagas novads",
          "name": "Dundagas novads"
        },
        {
          "id": 392,
          "code": "Durbes novads",
          "name": "Durbes novads"
        },
        {
          "id": 393,
          "code": "Engures novads",
          "name": "Engures novads"
        },
        {
          "id": 472,
          "code": "Ērgļu novads",
          "name": "Ērgļu novads"
        },
        {
          "id": 394,
          "code": "Garkalnes novads",
          "name": "Garkalnes novads"
        },
        {
          "id": 395,
          "code": "Grobiņas novads",
          "name": "Grobiņas novads"
        },
        {
          "id": 396,
          "code": "LV-GU",
          "name": "Gulbenes novads"
        },
        {
          "id": 397,
          "code": "Iecavas novads",
          "name": "Iecavas novads"
        },
        {
          "id": 398,
          "code": "Ikšķiles novads",
          "name": "Ikšķiles novads"
        },
        {
          "id": 399,
          "code": "Ilūkstes novads",
          "name": "Ilūkstes novads"
        },
        {
          "id": 400,
          "code": "Inčukalna novads",
          "name": "Inčukalna novads"
        },
        {
          "id": 401,
          "code": "Jaunjelgavas novads",
          "name": "Jaunjelgavas novads"
        },
        {
          "id": 402,
          "code": "Jaunpiebalgas novads",
          "name": "Jaunpiebalgas novads"
        },
        {
          "id": 403,
          "code": "Jaunpils novads",
          "name": "Jaunpils novads"
        },
        {
          "id": 357,
          "code": "Jēkabpils",
          "name": "Jēkabpils"
        },
        {
          "id": 405,
          "code": "LV-JK",
          "name": "Jēkabpils novads"
        },
        {
          "id": 356,
          "code": "LV-JEL",
          "name": "Jelgava"
        },
        {
          "id": 404,
          "code": "LV-JL",
          "name": "Jelgavas novads"
        },
        {
          "id": 358,
          "code": "LV-JUR",
          "name": "Jūrmala"
        },
        {
          "id": 406,
          "code": "Kandavas novads",
          "name": "Kandavas novads"
        },
        {
          "id": 412,
          "code": "Kārsavas novads",
          "name": "Kārsavas novads"
        },
        {
          "id": 473,
          "code": "Ķeguma novads",
          "name": "Ķeguma novads"
        },
        {
          "id": 474,
          "code": "Ķekavas novads",
          "name": "Ķekavas novads"
        },
        {
          "id": 407,
          "code": "Kokneses novads",
          "name": "Kokneses novads"
        },
        {
          "id": 410,
          "code": "LV-KR",
          "name": "Krāslavas novads"
        },
        {
          "id": 408,
          "code": "Krimuldas novads",
          "name": "Krimuldas novads"
        },
        {
          "id": 409,
          "code": "Krustpils novads",
          "name": "Krustpils novads"
        },
        {
          "id": 411,
          "code": "LV-KU",
          "name": "Kuldīgas novads"
        },
        {
          "id": 413,
          "code": "Lielvārdes novads",
          "name": "Lielvārdes novads"
        },
        {
          "id": 359,
          "code": "LV-LPX",
          "name": "Liepāja"
        },
        {
          "id": 360,
          "code": "LV-LE",
          "name": "Liepājas novads"
        },
        {
          "id": 417,
          "code": "Līgatnes novads",
          "name": "Līgatnes novads"
        },
        {
          "id": 414,
          "code": "LV-LM",
          "name": "Limbažu novads"
        },
        {
          "id": 418,
          "code": "Līvānu novads",
          "name": "Līvānu novads"
        },
        {
          "id": 415,
          "code": "Lubānas novads",
          "name": "Lubānas novads"
        },
        {
          "id": 416,
          "code": "LV-LU",
          "name": "Ludzas novads"
        },
        {
          "id": 419,
          "code": "LV-MA",
          "name": "Madonas novads"
        },
        {
          "id": 421,
          "code": "Mālpils novads",
          "name": "Mālpils novads"
        },
        {
          "id": 422,
          "code": "Mārupes novads",
          "name": "Mārupes novads"
        },
        {
          "id": 420,
          "code": "Mazsalacas novads",
          "name": "Mazsalacas novads"
        },
        {
          "id": 423,
          "code": "Naukšēnu novads",
          "name": "Naukšēnu novads"
        },
        {
          "id": 424,
          "code": "Neretas novads",
          "name": "Neretas novads"
        },
        {
          "id": 425,
          "code": "Nīcas novads",
          "name": "Nīcas novads"
        },
        {
          "id": 426,
          "code": "LV-OG",
          "name": "Ogres novads"
        },
        {
          "id": 427,
          "code": "Olaines novads",
          "name": "Olaines novads"
        },
        {
          "id": 428,
          "code": "Ozolnieku novads",
          "name": "Ozolnieku novads"
        },
        {
          "id": 432,
          "code": "Pārgaujas novads",
          "name": "Pārgaujas novads"
        },
        {
          "id": 433,
          "code": "Pāvilostas novads",
          "name": "Pāvilostas novads"
        },
        {
          "id": 434,
          "code": "Pļaviņu novads",
          "name": "Pļaviņu novads"
        },
        {
          "id": 429,
          "code": "LV-PR",
          "name": "Preiļu novads"
        },
        {
          "id": 430,
          "code": "Priekules novads",
          "name": "Priekules novads"
        },
        {
          "id": 431,
          "code": "Priekuļu novads",
          "name": "Priekuļu novads"
        },
        {
          "id": 435,
          "code": "Raunas novads",
          "name": "Raunas novads"
        },
        {
          "id": 361,
          "code": "LV-REZ",
          "name": "Rēzekne"
        },
        {
          "id": 442,
          "code": "LV-RE",
          "name": "Rēzeknes novads"
        },
        {
          "id": 436,
          "code": "Riebiņu novads",
          "name": "Riebiņu novads"
        },
        {
          "id": 362,
          "code": "LV-RIX",
          "name": "Rīga"
        },
        {
          "id": 363,
          "code": "LV-RI",
          "name": "Rīgas novads"
        },
        {
          "id": 437,
          "code": "Rojas novads",
          "name": "Rojas novads"
        },
        {
          "id": 438,
          "code": "Ropažu novads",
          "name": "Ropažu novads"
        },
        {
          "id": 439,
          "code": "Rucavas novads",
          "name": "Rucavas novads"
        },
        {
          "id": 440,
          "code": "Rugāju novads",
          "name": "Rugāju novads"
        },
        {
          "id": 443,
          "code": "Rūjienas novads",
          "name": "Rūjienas novads"
        },
        {
          "id": 441,
          "code": "Rundāles novads",
          "name": "Rundāles novads"
        },
        {
          "id": 444,
          "code": "Salacgrīvas novads",
          "name": "Salacgrīvas novads"
        },
        {
          "id": 445,
          "code": "Salas novads",
          "name": "Salas novads"
        },
        {
          "id": 446,
          "code": "Salaspils novads",
          "name": "Salaspils novads"
        },
        {
          "id": 447,
          "code": "LV-SA",
          "name": "Saldus novads"
        },
        {
          "id": 448,
          "code": "Saulkrastu novads",
          "name": "Saulkrastu novads"
        },
        {
          "id": 455,
          "code": "Sējas novads",
          "name": "Sējas novads"
        },
        {
          "id": 449,
          "code": "Siguldas novads",
          "name": "Siguldas novads"
        },
        {
          "id": 451,
          "code": "Skrīveru novads",
          "name": "Skrīveru novads"
        },
        {
          "id": 450,
          "code": "Skrundas novads",
          "name": "Skrundas novads"
        },
        {
          "id": 452,
          "code": "Smiltenes novads",
          "name": "Smiltenes novads"
        },
        {
          "id": 453,
          "code": "Stopiņu novads",
          "name": "Stopiņu novads"
        },
        {
          "id": 454,
          "code": "Strenču novads",
          "name": "Strenču novads"
        },
        {
          "id": 456,
          "code": "LV-TA",
          "name": "Talsu novads"
        },
        {
          "id": 458,
          "code": "Tērvetes novads",
          "name": "Tērvetes novads"
        },
        {
          "id": 457,
          "code": "LV-TU",
          "name": "Tukuma novads"
        },
        {
          "id": 459,
          "code": "Vaiņodes novads",
          "name": "Vaiņodes novads"
        },
        {
          "id": 460,
          "code": "LV-VK",
          "name": "Valkas novads"
        },
        {
          "id": 364,
          "code": "Valmiera",
          "name": "Valmiera"
        },
        {
          "id": 461,
          "code": "LV-VM",
          "name": "Valmieras novads"
        },
        {
          "id": 462,
          "code": "Varakļānu novads",
          "name": "Varakļānu novads"
        },
        {
          "id": 469,
          "code": "Vārkavas novads",
          "name": "Vārkavas novads"
        },
        {
          "id": 463,
          "code": "Vecpiebalgas novads",
          "name": "Vecpiebalgas novads"
        },
        {
          "id": 464,
          "code": "Vecumnieku novads",
          "name": "Vecumnieku novads"
        },
        {
          "id": 365,
          "code": "LV-VEN",
          "name": "Ventspils"
        },
        {
          "id": 465,
          "code": "LV-VE",
          "name": "Ventspils novads"
        },
        {
          "id": 466,
          "code": "Viesītes novads",
          "name": "Viesītes novads"
        },
        {
          "id": 467,
          "code": "Viļakas novads",
          "name": "Viļakas novads"
        },
        {
          "id": 468,
          "code": "Viļānu novads",
          "name": "Viļānu novads"
        },
        {
          "id": 470,
          "code": "Zilupes novads",
          "name": "Zilupes novads"
        }
      ]
    },
    {
      "id": "NL",
      "full_name_english": "Netherlands",
      "available_regions": null
    },
    {
      "id": "PL",
      "full_name_english": "Poland",
      "available_regions": [
        {
          "id": 1018,
          "code": "PL-02",
          "name": "dolnośląskie"
        },
        {
          "id": 1019,
          "code": "PL-04",
          "name": "kujawsko-pomorskie"
        },
        {
          "id": 1020,
          "code": "PL-06",
          "name": "lubelskie"
        },
        {
          "id": 1021,
          "code": "PL-08",
          "name": "lubuskie"
        },
        {
          "id": 1024,
          "code": "PL-14",
          "name": "mazowieckie"
        },
        {
          "id": 1023,
          "code": "PL-12",
          "name": "małopolskie"
        },
        {
          "id": 1025,
          "code": "PL-16",
          "name": "opolskie"
        },
        {
          "id": 1026,
          "code": "PL-18",
          "name": "podkarpackie"
        },
        {
          "id": 1027,
          "code": "PL-20",
          "name": "podlaskie"
        },
        {
          "id": 1028,
          "code": "PL-22",
          "name": "pomorskie"
        },
        {
          "id": 1029,
          "code": "PL-24",
          "name": "śląskie"
        },
        {
          "id": 1030,
          "code": "PL-26",
          "name": "świętokrzyskie"
        },
        {
          "id": 1031,
          "code": "PL-28",
          "name": "warmińsko-mazurskie"
        },
        {
          "id": 1032,
          "code": "PL-30",
          "name": "wielkopolskie"
        },
        {
          "id": 1033,
          "code": "PL-32",
          "name": "zachodniopomorskie"
        },
        {
          "id": 1022,
          "code": "PL-10",
          "name": "łódzkie"
        }
      ]
    },
    {
      "id": "PT",
      "full_name_english": "Portugal",
      "available_regions": [
        {
          "id": 1034,
          "code": "PT-01",
          "name": "Aveiro"
        },
        {
          "id": 1035,
          "code": "PT-02",
          "name": "Beja"
        },
        {
          "id": 1036,
          "code": "PT-03",
          "name": "Braga"
        },
        {
          "id": 1037,
          "code": "PT-04",
          "name": "Bragança"
        },
        {
          "id": 1038,
          "code": "PT-05",
          "name": "Castelo Branco"
        },
        {
          "id": 1039,
          "code": "PT-06",
          "name": "Coimbra"
        },
        {
          "id": 1040,
          "code": "PT-07",
          "name": "Évora"
        },
        {
          "id": 1041,
          "code": "PT-08",
          "name": "Faro"
        },
        {
          "id": 1042,
          "code": "PT-09",
          "name": "Guarda"
        },
        {
          "id": 1043,
          "code": "PT-10",
          "name": "Leiria"
        },
        {
          "id": 1044,
          "code": "PT-11",
          "name": "Lisboa"
        },
        {
          "id": 1045,
          "code": "PT-12",
          "name": "Portalegre"
        },
        {
          "id": 1046,
          "code": "PT-13",
          "name": "Porto"
        },
        {
          "id": 1053,
          "code": "PT-30",
          "name": "Região Autónoma da Madeira"
        },
        {
          "id": 1052,
          "code": "PT-20",
          "name": "Região Autónoma dos Açores"
        },
        {
          "id": 1047,
          "code": "PT-14",
          "name": "Santarém"
        },
        {
          "id": 1048,
          "code": "PT-15",
          "name": "Setúbal"
        },
        {
          "id": 1049,
          "code": "PT-16",
          "name": "Viana do Castelo"
        },
        {
          "id": 1050,
          "code": "PT-17",
          "name": "Vila Real"
        },
        {
          "id": 1051,
          "code": "PT-18",
          "name": "Viseu"
        }
      ]
    },
    {
      "id": "RO",
      "full_name_english": "Romania",
      "available_regions": [
        {
          "id": 278,
          "code": "AB",
          "name": "Alba"
        },
        {
          "id": 279,
          "code": "AR",
          "name": "Arad"
        },
        {
          "id": 280,
          "code": "AG",
          "name": "Argeş"
        },
        {
          "id": 281,
          "code": "BC",
          "name": "Bacău"
        },
        {
          "id": 282,
          "code": "BH",
          "name": "Bihor"
        },
        {
          "id": 283,
          "code": "BN",
          "name": "Bistriţa-Năsăud"
        },
        {
          "id": 284,
          "code": "BT",
          "name": "Botoşani"
        },
        {
          "id": 286,
          "code": "BR",
          "name": "Brăila"
        },
        {
          "id": 285,
          "code": "BV",
          "name": "Braşov"
        },
        {
          "id": 287,
          "code": "B",
          "name": "Bucureşti"
        },
        {
          "id": 288,
          "code": "BZ",
          "name": "Buzău"
        },
        {
          "id": 290,
          "code": "CL",
          "name": "Călăraşi"
        },
        {
          "id": 289,
          "code": "CS",
          "name": "Caraş-Severin"
        },
        {
          "id": 291,
          "code": "CJ",
          "name": "Cluj"
        },
        {
          "id": 292,
          "code": "CT",
          "name": "Constanţa"
        },
        {
          "id": 293,
          "code": "CV",
          "name": "Covasna"
        },
        {
          "id": 294,
          "code": "DB",
          "name": "Dâmboviţa"
        },
        {
          "id": 295,
          "code": "DJ",
          "name": "Dolj"
        },
        {
          "id": 296,
          "code": "GL",
          "name": "Galaţi"
        },
        {
          "id": 297,
          "code": "GR",
          "name": "Giurgiu"
        },
        {
          "id": 298,
          "code": "GJ",
          "name": "Gorj"
        },
        {
          "id": 299,
          "code": "HR",
          "name": "Harghita"
        },
        {
          "id": 300,
          "code": "HD",
          "name": "Hunedoara"
        },
        {
          "id": 301,
          "code": "IL",
          "name": "Ialomiţa"
        },
        {
          "id": 302,
          "code": "IS",
          "name": "Iaşi"
        },
        {
          "id": 303,
          "code": "IF",
          "name": "Ilfov"
        },
        {
          "id": 304,
          "code": "MM",
          "name": "Maramureş"
        },
        {
          "id": 305,
          "code": "MH",
          "name": "Mehedinţi"
        },
        {
          "id": 306,
          "code": "MS",
          "name": "Mureş"
        },
        {
          "id": 307,
          "code": "NT",
          "name": "Neamţ"
        },
        {
          "id": 308,
          "code": "OT",
          "name": "Olt"
        },
        {
          "id": 309,
          "code": "PH",
          "name": "Prahova"
        },
        {
          "id": 311,
          "code": "SJ",
          "name": "Sălaj"
        },
        {
          "id": 310,
          "code": "SM",
          "name": "Satu-Mare"
        },
        {
          "id": 312,
          "code": "SB",
          "name": "Sibiu"
        },
        {
          "id": 313,
          "code": "SV",
          "name": "Suceava"
        },
        {
          "id": 314,
          "code": "TR",
          "name": "Teleorman"
        },
        {
          "id": 315,
          "code": "TM",
          "name": "Timiş"
        },
        {
          "id": 316,
          "code": "TL",
          "name": "Tulcea"
        },
        {
          "id": 318,
          "code": "VL",
          "name": "Vâlcea"
        },
        {
          "id": 317,
          "code": "VS",
          "name": "Vaslui"
        },
        {
          "id": 319,
          "code": "VN",
          "name": "Vrancea"
        }
      ]
    },
    {
      "id": "SE",
      "full_name_english": "Sweden",
      "available_regions": [
        {
          "id": 1064,
          "code": "SE-K",
          "name": "Blekinge län"
        },
        {
          "id": 1065,
          "code": "SE-W",
          "name": "Dalarnas län"
        },
        {
          "id": 1067,
          "code": "SE-X",
          "name": "Gävleborgs län"
        },
        {
          "id": 1066,
          "code": "SE-I",
          "name": "Gotlands län"
        },
        {
          "id": 1068,
          "code": "SE-N",
          "name": "Hallands län"
        },
        {
          "id": 1069,
          "code": "SE-Z",
          "name": "Jämtlands län"
        },
        {
          "id": 1070,
          "code": "SE-F",
          "name": "Jönköpings län"
        },
        {
          "id": 1071,
          "code": "SE-H",
          "name": "Kalmar län"
        },
        {
          "id": 1072,
          "code": "SE-G",
          "name": "Kronobergs län"
        },
        {
          "id": 1073,
          "code": "SE-BD",
          "name": "Norrbottens län"
        },
        {
          "id": 1083,
          "code": "SE-T",
          "name": "Örebro län"
        },
        {
          "id": 1084,
          "code": "SE-E",
          "name": "Östergötlands län"
        },
        {
          "id": 1074,
          "code": "SE-M",
          "name": "Skåne län"
        },
        {
          "id": 1076,
          "code": "SE-D",
          "name": "Södermanlands län"
        },
        {
          "id": 1075,
          "code": "SE-AB",
          "name": "Stockholms län"
        },
        {
          "id": 1077,
          "code": "SE-C",
          "name": "Uppsala län"
        },
        {
          "id": 1078,
          "code": "SE-S",
          "name": "Värmlands län"
        },
        {
          "id": 1079,
          "code": "SE-AC",
          "name": "Västerbottens län"
        },
        {
          "id": 1080,
          "code": "SE-Y",
          "name": "Västernorrlands län"
        },
        {
          "id": 1081,
          "code": "SE-U",
          "name": "Västmanlands län"
        },
        {
          "id": 1082,
          "code": "SE-O",
          "name": "Västra Götalands län"
        }
      ]
    },
    {
      "id": "SI",
      "full_name_english": "Slovenia",
      "available_regions": null
    },
    {
      "id": "SK",
      "full_name_english": "Slovakia",
      "available_regions": null
    }
  ]
}