{
  "posts": {
    "edges": [
      {
        "node": {
          "id": "cG9zdDo0MTM3",
          "title": "Gaming PC selber zusammenstellen: Eine Schritt-für-Schritt-Anleitung",
          "slug": "gaming-pc-selber-zusammenstellen-eine-schritt-fur-schritt-anleitung",
          "date": "2025-03-05T11:05:50",
          "excerpt": "<p>Einen&nbsp;Gaming PC selber zusammenstellen&nbsp;ist eine lohnende Erfahrung, die nicht nur Spaß macht, sondern auch die Möglichkeit bietet, ein System nach den eigenen Bedürfnissen und dem<a class=\"moretag\" href=\"http://cls-blog.nz/gaming-pc-selber-zusammenstellen-eine-schritt-fur-schritt-anleitung/\">.. Read more</a></p>\n",
          "featuredImage": {
            "node": {
              "sourceUrl": "http://cls-blog.nz/wp-content/uploads/2024/09/Wo-kann-man-PC-Konfiguratoren-kaufen-Die-besten-Plattformen-im-Uberblick.webp",
              "altText": "Wo kann man PC Konfiguratoren kaufen Die besten Plattformen im Überblick"
            }
          }
        }
      },
      {
        "node": {
          "id": "cG9zdDo0MDcx",
          "title": "Die Besten Desktop PC 2025",
          "slug": "die-besten-desktop-pc-2025",
          "date": "2025-03-05T05:09:49",
          "excerpt": "<p>Desktop-PCs bleiben auch im Jahr 2025 eine zentrale Säule der Technologie, sei es für professionelle Anwendungen, Gaming oder den privaten Gebrauch. Mit ständigen Fortschritten in<a class=\"moretag\" href=\"http://cls-blog.nz/die-besten-desktop-pc-2025/\">.. Read more</a></p>\n",
          "featuredImage": {
            "node": {
              "sourceUrl": "http://cls-blog.nz/wp-content/uploads/2025/03/Desktop-PCS-scaled.jpg",
              "altText": "Desktop PCS"
            }
          }
        }
      },
      {
        "node": {
          "id": "cG9zdDo0MDY3",
          "title": "Die Besten CAD-Laptops bei CLS-Computer",
          "slug": "die-besten-cad-laptops-bei-cls-computer",
          "date": "2025-03-04T11:42:02",
          "excerpt": "<p>Professionelle CAD-Laptops sind essenziell für Ingenieure, Architekten und Designer, die mit anspruchsvoller Software wie AutoCAD, SolidWorks, Revit oder Fusion 360 arbeiten. Diese Programme erfordern eine<a class=\"moretag\" href=\"http://cls-blog.nz/die-besten-cad-laptops-bei-cls-computer/\">.. Read more</a></p>\n",
          "featuredImage": {
            "node": {
              "sourceUrl": "http://cls-blog.nz/wp-content/uploads/2025/02/CAD-PC.webp",
              "altText": "CAD-PC Kaufberatung: Leistungsstarke Rechner für Ingenieure und Architekten"
            }
          }
        }
      },
      {
        "node": {
          "id": "cG9zdDo0MDcw",
          "title": "Die Besten Silent PC 2025",
          "slug": "die-besten-silent-pc-2025",
          "date": "2025-03-04T10:03:08",
          "excerpt": "<p>Ein leiser Computer ist nicht nur ein Luxus, sondern für viele eine Notwendigkeit. Ob für konzentriertes Arbeiten, entspanntes Streaming oder professionelle Grafikbearbeitung – ein lautloser<a class=\"moretag\" href=\"http://cls-blog.nz/die-besten-silent-pc-2025/\">.. Read more</a></p>\n",
          "featuredImage": {
            "node": {
              "sourceUrl": "http://cls-blog.nz/wp-content/uploads/2024/12/Silent-PC-scaled.jpg",
              "altText": "Silent PC"
            }
          }
        }
      }
    ]
  }
}